Metadata-Version: 2.4
Name: agentops-ai
Version: 1.4.1
Summary: AI-powered development platform: Multi-agent system for requirements discovery, conversational document building, and test automation
Author-email: Karthik Naig <agentops_info@protonmail.com>
Maintainer-email: Karthik Naig <agentops_info@protonmail.com>
License-Expression: MIT
Project-URL: Homepage, https://github.com/knaig/agentops_ai
Project-URL: Repository, https://github.com/knaig/agentops_ai
Project-URL: Documentation, https://github.com/knaig/agentops_ai/tree/main/docs
Project-URL: Issues, https://github.com/knaig/agentops_ai/issues
Keywords: testing,requirements,ai,automation,code-analysis,test-generation,qa,quality-assurance,multi-agent,openai,pytest,test-automation,requirements-traceability,conversational-ai,document-building,canvas-ux,requirements-discovery,human-in-the-loop,streamlit,chatgpt-style,builder-platform
Classifier: Development Status :: 4 - Beta
Classifier: Intended Audience :: Developers
Classifier: Intended Audience :: Information Technology
Classifier: Operating System :: OS Independent
Classifier: Programming Language :: Python :: 3
Classifier: Programming Language :: Python :: 3.8
Classifier: Programming Language :: Python :: 3.9
Classifier: Programming Language :: Python :: 3.10
Classifier: Programming Language :: Python :: 3.11
Classifier: Programming Language :: Python :: 3.12
Classifier: Programming Language :: Python :: 3.13
Classifier: Topic :: Software Development :: Testing
Classifier: Topic :: Software Development :: Testing :: Unit
Classifier: Topic :: Software Development :: Libraries :: Python Modules
Classifier: Topic :: Software Development :: Quality Assurance
Classifier: Topic :: Scientific/Engineering :: Artificial Intelligence
Classifier: Framework :: Pytest
Classifier: Environment :: Console
Classifier: Environment :: Console :: Curses
Requires-Python: >=3.8
Requires-Dist: click>=8.1.3
Requires-Dist: rich>=13.3.5
Requires-Dist: openai>=1.0.0
Requires-Dist: python-dotenv>=1.1.0
Requires-Dist: langchain_openai>=0.0.1
Requires-Dist: fastapi>=0.100.0
Requires-Dist: uvicorn>=0.23.0
Requires-Dist: pandas>=1.5.0
Requires-Dist: jinja2>=3.1.0
Requires-Dist: markdown>=3.4.0
Requires-Dist: sqlalchemy>=1.4.0
Requires-Dist: pytest>=7.0.0
Requires-Dist: weasyprint>=65.0
Requires-Dist: python-docx>=1.2.0
Requires-Dist: streamlit>=1.28.0
Requires-Dist: pydantic>=2.0.0
Requires-Dist: typing-extensions>=4.0.0
Requires-Dist: questionary>=2.0.0
Provides-Extra: dev
Requires-Dist: pytest>=8.3.5; extra == "dev"
Requires-Dist: pytest-json-report>=1.5.0; extra == "dev"
Requires-Dist: coverage>=7.8.2; extra == "dev"
Requires-Dist: pydoc-markdown>=4.7.0; extra == "dev"
Requires-Dist: mkdocs-material>=9.4.0; extra == "dev"
Requires-Dist: mkdocs>=1.5.0; extra == "dev"
Requires-Dist: ruff>=0.1.0; extra == "dev"
Requires-Dist: black>=23.0.0; extra == "dev"
Requires-Dist: pydocstyle>=6.3.0; extra == "dev"
